sinker/__init__.py
sinker/__main__.py
sinker/bulk_action_generator.py
sinker/es.py
sinker/query_templates.py
sinker/runner.py
sinker/settings.py
sinker/sinker.py
sinker/utils.py
sinker-0.1.4.dist-info/LICENSE-APACHE
sinker-0.1.4.dist-info/LICENSE-MIT
sinker-0.1.4.dist-info/METADATA
sinker-0.1.4.dist-info/WHEEL
sinker-0.1.4.dist-info/entry_points.txt
sinker-0.1.4.dist-info/RECORD
