Metadata-Version: 2.1
Name: sinker
Version: 0.1.4
Summary: Synchronize Postgres to Elasticsearch
License: MIT/Apache-2.0
Author: Loren Siebert
Author-email: loren@paradigm.xyz
Requires-Python: >=3.9,<4.0
Classifier: License :: Other/Proprietary License
Classifier: Programming Language :: Python :: 3
Classifier: Programming Language :: Python :: 3.9
Classifier: Programming Language :: Python :: 3.10
Classifier: Programming Language :: Python :: 3.11
Classifier: Programming Language :: Python :: 3.12
Classifier: Programming Language :: Python :: 3.13
Requires-Dist: elasticsearch (>=8.17.0,<9.0.0)
Requires-Dist: environs (>=9.5,<15.0)
Requires-Dist: psycopg (>=3.1.8,<4.0.0)
Requires-Dist: pytest-mock (>=3.10.0,<4.0.0)
Requires-Dist: sqlglot (>=26.2.1,<27.0.0)
